ksearch/__init__.py
ksearch/classify.py
ksearch/collectors.py
ksearch/columns.py
ksearch/compat.py
ksearch/externalsort.py
ksearch/fields.py
ksearch/formats.py
ksearch/highlight.py
ksearch/idsets.py
ksearch/index.py
ksearch/legacy.py
ksearch/multiproc.py
ksearch/reading.py
ksearch/scoring.py
ksearch/searching.py
ksearch/sorting.py
ksearch/spelling.py
ksearch/system.py
ksearch/writing.py
ksearch/analysis/__init__.py
ksearch/analysis/acore.py
ksearch/analysis/analyzers.py
ksearch/analysis/filters.py
ksearch/analysis/intraword.py
ksearch/analysis/morph.py
ksearch/analysis/ngrams.py
ksearch/analysis/tokenizers.py
ksearch/automata/__init__.py
ksearch/automata/fsa.py
ksearch/automata/glob.py
ksearch/automata/lev.py
ksearch/automata/nfa.py
ksearch/automata/reg.py
ksearch/codec/__init__.py
ksearch/codec/base.py
ksearch/codec/memory.py
ksearch/codec/plaintext.py
ksearch/codec/whoosh3.py
ksearch/filedb/__init__.py
ksearch/filedb/compound.py
ksearch/filedb/filestore.py
ksearch/filedb/filetables.py
ksearch/filedb/gae.py
ksearch/filedb/structfile.py
ksearch/lang/__init__.py
ksearch/lang/dmetaphone.py
ksearch/lang/isri.py
ksearch/lang/lovins.py
ksearch/lang/morph_en.py
ksearch/lang/paicehusk.py
ksearch/lang/phonetic.py
ksearch/lang/porter.py
ksearch/lang/porter2.py
ksearch/lang/stopwords.py
ksearch/lang/wordnet.py
ksearch/lang/snowball/__init__.py
ksearch/lang/snowball/bases.py
ksearch/lang/snowball/danish.py
ksearch/lang/snowball/dutch.py
ksearch/lang/snowball/english.py
ksearch/lang/snowball/finnish.py
ksearch/lang/snowball/french.py
ksearch/lang/snowball/german.py
ksearch/lang/snowball/hungarian.py
ksearch/lang/snowball/italian.py
ksearch/lang/snowball/norwegian.py
ksearch/lang/snowball/portugese.py
ksearch/lang/snowball/romanian.py
ksearch/lang/snowball/russian.py
ksearch/lang/snowball/spanish.py
ksearch/lang/snowball/swedish.py
ksearch/matching/__init__.py
ksearch/matching/binary.py
ksearch/matching/combo.py
ksearch/matching/mcore.py
ksearch/matching/wrappers.py
ksearch-3.0.0.dist-info/METADATA
ksearch-3.0.0.dist-info/WHEEL
ksearch-3.0.0.dist-info/top_level.txt
ksearch-3.0.0.dist-info/zip-safe
ksearch-3.0.0.dist-info/RECORD
